mark_filter/__init__.py
mark_filter/plugin.py
pytest_mark_filter-0.1.2.dist-info/METADATA
pytest_mark_filter-0.1.2.dist-info/WHEEL
pytest_mark_filter-0.1.2.dist-info/entry_points.txt
pytest_mark_filter-0.1.2.dist-info/licenses/LICENSE
pytest_mark_filter-0.1.2.dist-info/RECORD
