Metadata-Version: 2.4
Name: pytest-mark-filter
Version: 0.1.2
Summary: Filter pytest marks by name using match kw
Project-URL: Homepage, https://github.com/ygorpontelo/pytest-mark-filter
Author-email: Ygor Pontelo <ygorpontelo@gmail.com>
License-Expression: MIT
License-File: LICENSE
Keywords: filter,mark,match,plugin
Classifier: Framework :: Pytest
Requires-Python: >=3.10
Requires-Dist: pytest>=8.3.0
